CourseComparator/__init__.py
CourseComparator/cc_classes.py
CourseComparator/cc_functions.py
coursecomparator-0.1.2.dist-info/licenses/LICENCE
coursecomparator-0.1.2.dist-info/METADATA
coursecomparator-0.1.2.dist-info/WHEEL
coursecomparator-0.1.2.dist-info/top_level.txt
coursecomparator-0.1.2.dist-info/RECORD
