Metadata-Version: 2.4
Name: CourseComparator
Version: 0.1.2
Summary: 用于比较不同的专业、届别或年级之间的课程设置，供转专业、降级学生确认可冲抵及需补修的课程。
Author-email: Vincy SHI <vincy@vincy1230.net>
License-Expression: MIT
Project-URL: Homepage, https://github.com/vincy1230/Course-Comparator
License-File: LICENCE
Dynamic: license-file
